[{"partido": "UNIDAD NACIONAL DE LA ESPERANZA", "votos": 7}, {"partido": "PARTIDO AZUL", "votos": 3}, {"partido": "VALOR UNIONISTA", "votos": 45}, {"partido": "CABAL", "votos": 28}, {"partido": "TODOS", "votos": 1}, {"partido": "VAMOS POR UNA GUATEMALA DIFERENTE", "votos": 4}, {"partido": "PARTIDO HUMANISTA DE GUATEMALA", "votos": 0}, {"partido": "PARTIDO REPUBLICANO", "votos": 3}, {"partido": "PARTIDO DE INTEGRACI\u00d3N NACIONAL", "votos": 4}, {"partido": "COMUNIDAD ELEFANTE", "votos": 2}, {"partido": "VICTORIA", "votos": 5}, {"partido": "MOVIMIENTO SEMILLA", "votos": 75}, {"partido": "FRENTE DE CONVERGENCIA NACIONAL", "votos": 1}, {"partido": "PARTIDO POLITICO NOSOTROS", "votos": 0}, {"partido": "UNION REPUBLICANA", "votos": 1}, {"partido": "URNG-MAIZ WINAQ", "votos": 2}, {"partido": "COMPROMISO, RENOVACION Y ORDEN", "votos": 5}, {"partido": "BIENESTAR NACIONAL", "votos": 19}, {"partido": "VISION CON VALORES", "votos": 3}, {"partido": "MI FAMILIA", "votos": 5}, {"partido": "CAMBIO", "votos": 1}, {"partido": "VOLUNTAD, OPORTUNIDAD Y SOLIDARIDAD", "votos": 23}, {"partido": "Total Votos V\u00e1lidos", "votos": 237}, {"partido": "Votos Nulos", "votos": 22}, {"partido": "Votos en Blanco", "votos": 0}, {"partido": "Total Votos V\u00e1lidamente Emitidos", "votos": 259}, {"partido": "Votos Inv\u00e1lidos", "votos": 0}, {"partido": "Total Votos", "votos": 259}, {"partido": "Impugnaciones", "votos": 0}, {"partido": "Cantidad de papeletas recibidas", "votos": 400}, {"partido": "Cantidad de papeletas no usadas", "votos": 141}, {"partido": "Ciudadanos que se presentaron a votar", "votos": 259}]